{
  "pass": true,
  "severity": "low",
  "issues": [],
  "summary": "O texto visivel esta em portugues europeu, adequado a alunos de 2.º ano e com instrucoes curtas. A regra de equivalencia nao e declarada no titulo nem na primeira instrucao; surge depois da comparacao entre 1/2 e 2/4.",
  "acceptance_checks": [
    "Ortografia e gramatica pt-PT AO90: OK",
    "Registo consistente: OK",
    "Adequacao a faixa etaria: OK",
    "Instrucoes claras e seguiveis: OK",
    "Alinhamento com objectivos: OK"
  ]
}
